marms/__init__.py
marms/email.py
marms/time.py
marms-1.1.0.dist-info/METADATA
marms-1.1.0.dist-info/WHEEL
marms-1.1.0.dist-info/top_level.txt
marms-1.1.0.dist-info/RECORD
