Metadata-Version: 2.1
Name: marms
Version: 1.1.0
Summary: my arms
Home-page: UNKNOWN
Author: Caturbhuja
Author-email: caturbhuja@foxmail.com
License: MIT
Platform: UNKNOWN
